sspqdd/__init__.py
sspqdd/sspqdd_pkg.py
sspqdd/models/converted_model.tflite
sspqdd-1.0.32.dist-info/METADATA
sspqdd-1.0.32.dist-info/PKG-INFO (DESKTOP-67JOARI's conflicted copy 2023-05-22)
sspqdd-1.0.32.dist-info/SOURCES (DESKTOP-67JOARI's conflicted copy 2023-05-22).txt
sspqdd-1.0.32.dist-info/WHEEL
sspqdd-1.0.32.dist-info/dependency_links (DESKTOP-67JOARI's conflicted copy 2023-05-22).txt
sspqdd-1.0.32.dist-info/top_level (DESKTOP-67JOARI's conflicted copy 2023-05-22).txt
sspqdd-1.0.32.dist-info/top_level.txt
sspqdd-1.0.32.dist-info/RECORD
