Metadata-Version: 2.1
Name: sspqdd
Version: 1.0.32
Summary: Single-Shot-Power-Quality-Disturbance-Detector
Home-page: UNKNOWN
Author: Carlos Iturrino-García
Author-email: carlos.iturrino.garcia@gmail.com
License: UNKNOWN
Platform: UNKNOWN
